linalg_fromscratch/__init__.py
linalg_fromscratch/cosine.py
linalg_fromscratch/pca.py
linalg_fromscratch-0.1.1.dist-info/METADATA
linalg_fromscratch-0.1.1.dist-info/WHEEL
linalg_fromscratch-0.1.1.dist-info/top_level.txt
linalg_fromscratch-0.1.1.dist-info/RECORD
