Metadata-Version: 2.4
Name: linalg-fromscratch
Version: 0.1.1
Summary: Cosine similarity and PCA (cov + SVD) from scratch in NumPy with tests
Author-email: Izew Dev Labs <izewdevlabs@gmail.com>
License: MIT
Project-URL: Homepage, https://github.com/Izewdevlabs/Cosine_PCA
Project-URL: Issues, https://github.com/Izewdevlabs/Cosine_PCA/issues
Keywords: numpy,linear algebra,pca,cosine similarity,education
Classifier: Programming Language :: Python :: 3
Classifier: License :: OSI Approved :: MIT License
Classifier: Operating System :: OS Independent
Requires-Python: >=3.9
Requires-Dist: numpy>=1.23
